pdfannots/__init__.py
pdfannots/__main__.py
pdfannots/cli.py
pdfannots/py.typed
pdfannots/types.py
pdfannots/utils.py
pdfannots/printer/__init__.py
pdfannots/printer/json.py
pdfannots/printer/markdown.py
pdfannots-0.5.dist-info/METADATA
pdfannots-0.5.dist-info/WHEEL
pdfannots-0.5.dist-info/entry_points.txt
pdfannots-0.5.dist-info/licenses/LICENSE.txt
pdfannots-0.5.dist-info/RECORD
