Metadata-Version: 2.4
Name: pdfannots
Version: 0.5
Summary: Tool to extract and pretty-print PDF annotations for reviewing
Project-URL: Homepage, https://github.com/0xabu/pdfannots
Author-email: Andrew Baumann <pdfannots.pypi.org@ab.id.au>
License: MIT License
License-File: LICENSE.txt
Classifier: Intended Audience :: Science/Research
Classifier: License :: OSI Approved :: MIT License
Classifier: Programming Language :: Python :: 3
Classifier: Programming Language :: Python :: 3.8
Classifier: Programming Language :: Python :: 3.9
Classifier: Programming Language :: Python :: 3.10
Classifier: Programming Language :: Python :: 3.11
Classifier: Programming Language :: Python :: 3.12
Classifier: Programming Language :: Python :: 3.13
Classifier: Topic :: Text Processing
Requires-Python: >=3.8
Requires-Dist: pdfminer-six!=20240706,>=20220319
